src/notcli/__init__.py
src/notcli/main.py
src/notcli/apps/__init__.py
src/notcli/apps/load_vars.py
src/notcli/conf/__init__.py
src/notcli/conf/settings.py
src/notcli/screens/__init__.py
src/notcli/screens/error.py
src/notcli/static/demo.css
src/notcli/static/modal.css
src/tty/ttyecho
notcli-0.0.10.dist-info/METADATA
notcli-0.0.10.dist-info/WHEEL
notcli-0.0.10.dist-info/entry_points.txt
notcli-0.0.10.dist-info/licenses/LICENSE
notcli-0.0.10.dist-info/RECORD
