Metadata-Version: 2.1
Name: notcli
Version: 0.0.10
Summary: Textual User Interface (TUI) application designed to streamline your command line tasks with easy-to-use shortcuts
Project-URL: Homepage, https://github.com/godd0t/notcli
License: MIT
License-File: LICENSE
Classifier: Development Status :: 1 - Planning
Classifier: Environment :: Console
Classifier: Intended Audience :: Developers
Classifier: Intended Audience :: Education
Classifier: License :: OSI Approved :: MIT License
Classifier: Operating System :: OS Independent
Classifier: Programming Language :: Python :: 3.10
Classifier: Programming Language :: Python :: 3.11
Classifier: Topic :: Software Development :: Libraries :: Python Modules
Classifier: Topic :: Software Development :: User Interfaces
Classifier: Topic :: Software Development :: Version Control :: Git
Classifier: Topic :: Text Processing
Classifier: Topic :: Utilities
Requires-Dist: textual[dev]==0.26.0
Provides-Extra: dev
Requires-Dist: black==23.3.0; extra == 'dev'
Requires-Dist: build==0.10.0; extra == 'dev'
Requires-Dist: coverage[toml]==7.2.6; extra == 'dev'
Requires-Dist: pytest-asyncio==0.21.0; extra == 'dev'
Requires-Dist: pytest-sugar==0.9.7; extra == 'dev'
Requires-Dist: pytest==7.3.1; extra == 'dev'
Requires-Dist: ruff==0.0.270; extra == 'dev'
Requires-Dist: twine==4.0.2; extra == 'dev'
